simbio/models/earm/__init__.py
simbio/models/earm/models/albeck.py
simbio/models/earm/models/albeck_as_matlab.py
simbio/models/earm/models/pore_transport.py
simbio_earm-0.1.0.dist-info/LICENSE
simbio_earm-0.1.0.dist-info/METADATA
simbio_earm-0.1.0.dist-info/WHEEL
simbio_earm-0.1.0.dist-info/top_level.txt
simbio_earm-0.1.0.dist-info/RECORD
