Metadata-Version: 2.1
Name: simbio-earm
Version: 0.1.0
Summary: Extrinsic Apoptotic Reaction Models
Author-email: Mauro Silberberg <maurosilber@gmail.com>
License: MIT License
Project-URL: Homepage, https://github.com/maurosilber/simbio-earm
Project-URL: Bug Tracker, https://github.com/maurosilber/simbio-earm/issues
Keywords: SimBio,EARM,apoptosis
Classifier: License :: OSI Approved :: MIT License
Classifier: Operating System :: OS Independent
Classifier: Programming Language :: Python :: 3
Requires-Python: >=3.7
License-File: LICENSE
Requires-Dist: simbio
